CHANGES.rst
CONTRIBUTORS.rst
DEVELOP.rst
LICENSE.GPL
LICENSE.rst
MANIFEST.in
README.rst
setup.cfg
setup.py
docs/conf.py
docs/index.rst
src/collective/__init__.py
src/collective.tabularlabeloverrides.egg-info/PKG-INFO
src/collective.tabularlabeloverrides.egg-info/SOURCES.txt
src/collective.tabularlabeloverrides.egg-info/dependency_links.txt
src/collective.tabularlabeloverrides.egg-info/entry_points.txt
src/collective.tabularlabeloverrides.egg-info/namespace_packages.txt
src/collective.tabularlabeloverrides.egg-info/not-zip-safe
src/collective.tabularlabeloverrides.egg-info/requires.txt
src/collective.tabularlabeloverrides.egg-info/top_level.txt
src/collective/tabularlabeloverrides/__init__.py
src/collective/tabularlabeloverrides/configure.zcml
src/collective/tabularlabeloverrides/interfaces.py
src/collective/tabularlabeloverrides/permissions.zcml
src/collective/tabularlabeloverrides/setuphandlers.py
src/collective/tabularlabeloverrides/testing.py
src/collective/tabularlabeloverrides/behaviors/__init__.py
src/collective/tabularlabeloverrides/behaviors/configure.zcml
src/collective/tabularlabeloverrides/behaviors/tabular_label_overrides.py
src/collective/tabularlabeloverrides/browser/__init__.py
src/collective/tabularlabeloverrides/browser/configure.zcml
src/collective/tabularlabeloverrides/browser/overrides/.gitkeep
src/collective/tabularlabeloverrides/browser/static/.gitkeep
src/collective/tabularlabeloverrides/locales/README.rst
src/collective/tabularlabeloverrides/locales/__init__.py
src/collective/tabularlabeloverrides/locales/collective.tabularlabeloverrides.pot
src/collective/tabularlabeloverrides/locales/update.py
src/collective/tabularlabeloverrides/locales/update.sh
src/collective/tabularlabeloverrides/locales/en/LC_MESSAGES/collective.tabularlabeloverrides.po
src/collective/tabularlabeloverrides/profiles/default/browserlayer.xml
src/collective/tabularlabeloverrides/profiles/default/catalog.xml
src/collective/tabularlabeloverrides/profiles/default/metadata.xml
src/collective/tabularlabeloverrides/profiles/default/rolemap.xml
src/collective/tabularlabeloverrides/profiles/default/types.xml
src/collective/tabularlabeloverrides/profiles/default/registry/main.xml
src/collective/tabularlabeloverrides/profiles/default/types/Collection.xml
src/collective/tabularlabeloverrides/profiles/uninstall/browserlayer.xml
src/collective/tabularlabeloverrides/tests/__init__.py
