Metadata-Version: 2.1
Name: collective.tabularlabeloverrides
Version: 1.0b4
Summary: Allows to override the labels for the tabular view on a Collection.
Home-page: https://github.com/collective/collective.tabularlabeloverrides
Author: Maik Derstappen
Author-email: md@derico.de
License: GPL version 2
Project-URL: PyPI, https://pypi.org/project/collective.tabularlabeloverrides/
Project-URL: Source, https://github.com/collective/collective.tabularlabeloverrides
Project-URL: Tracker, https://github.com/collective/collective.tabularlabeloverrides/issues
Keywords: Python Plone CMS
Classifier: Environment :: Web Environment
Classifier: Framework :: Plone
Classifier: Framework :: Plone :: Addon
Classifier: Framework :: Plone :: 5.2
Classifier: Framework :: Plone :: 6.0
Classifier: Programming Language :: Python
Classifier: Programming Language :: Python :: 3.7
Classifier: Programming Language :: Python :: 3.8
Classifier: Programming Language :: Python :: 3.9
Classifier: Programming Language :: Python :: 3.10
Classifier: Programming Language :: Python :: 3.11
Classifier: Operating System :: OS Independent
Classifier: License :: OSI Approved :: GNU General Public License v2 (GPLv2)
Requires-Python: >=3.7
Provides-Extra: test
License-File: LICENSE.GPL
License-File: LICENSE.rst
